{"total_count":6,"jobs":[{"id":20128870175,"run_id":7398824388,"run_url":"https://api.github.com/repos/mongodb/mongodb-atlas-kubernetes/actions/runs/7398824388","node_id":"CR_kwDOEnYpJ88AAAAEr8YvHw","head_branch":"CLOUDP-209691/oidc-auth-support","head_sha":"cf26f107757d32b3ae162bfab3f2b668d6648f5c","url":"https://api.github.com/repos/mongodb/mongodb-atlas-kubernetes/actions/jobs/20128870175","html_url":"https://github.com/mongodb/mongodb-atlas-kubernetes/actions/runs/7398824388/job/20128870175","status":"completed","conclusion":"success","created_at":"2024-01-03T14:58:32Z","started_at":"2024-01-03T14:58:38Z","completed_at":"2024-01-03T14:58:55Z","name":"validate-manifests / Validate Manifests","steps":[{"name":"Set up job","status":"completed","conclusion":"success","number":1,"started_at":"2024-01-03T14:58:37Z","completed_at":"2024-01-03T14:58:38Z"},{"name":"Run actions/checkout@v4","status":"completed","conclusion":"success","number":2,"started_at":"2024-01-03T14:58:38Z","completed_at":"2024-01-03T14:58:39Z"},{"name":"Cache multiple paths","status":"completed","conclusion":"success","number":3,"started_at":"2024-01-03T14:58:40Z","completed_at":"2024-01-03T14:58:47Z"},{"name":"Setup Go","status":"completed","conclusion":"success","number":4,"started_at":"2024-01-03T14:58:48Z","completed_at":"2024-01-03T14:58:48Z"},{"name":"Install dependencies","status":"completed","conclusion":"success","number":5,"started_at":"2024-01-03T14:58:48Z","completed_at":"2024-01-03T14:58:49Z"},{"name":"Run testing","status":"completed","conclusion":"success","number":6,"started_at":"2024-01-03T14:58:49Z","completed_at":"2024-01-03T14:58:52Z"},{"name":"Post Setup Go","status":"completed","conclusion":"success","number":10,"started_at":"2024-01-03T14:58:52Z","completed_at":"2024-01-03T14:58:52Z"},{"name":"Post Cache multiple paths","status":"completed","conclusion":"success","number":11,"started_at":"2024-01-03T14:58:55Z","completed_at":"2024-01-03T14:58:55Z"},{"name":"Post Run actions/checkout@v4","status":"completed","conclusion":"success","number":12,"started_at":"2024-01-03T14:58:55Z","completed_at":"2024-01-03T14:58:55Z"},{"name":"Complete job","status":"completed","conclusion":"success","number":13,"started_at":"2024-01-03T14:58:53Z","completed_at":"2024-01-03T14:58:53Z"}],"check_run_url":"https://api.github.com/repos/mongodb/mongodb-atlas-kubernetes/check-runs/20128870175","labels":["ubuntu-latest"],"runner_id":4,"runner_name":"GitHub Actions 4","runner_group_id":2,"runner_group_name":"GitHub Actions","run_attempt":1,"workflow_name":"Test"},{"id":20128870430,"run_id":7398824388,"run_url":"https://api.github.com/repos/mongodb/mongodb-atlas-kubernetes/actions/runs/7398824388","node_id":"CR_kwDOEnYpJ88AAAAEr8YwHg","head_branch":"CLOUDP-209691/oidc-auth-support","head_sha":"cf26f107757d32b3ae162bfab3f2b668d6648f5c","url":"https://api.github.com/repos/mongodb/mongodb-atlas-kubernetes/actions/jobs/20128870430","html_url":"https://github.com/mongodb/mongodb-atlas-kubernetes/actions/runs/7398824388/job/20128870430","status":"completed","conclusion":"failure","created_at":"2024-01-03T14:58:33Z","started_at":"2024-01-03T14:58:38Z","completed_at":"2024-01-03T15:02:08Z","name":"lint / lint","steps":[{"name":"Set up job","status":"completed","conclusion":"success","number":1,"started_at":"2024-01-03T14:58:38Z","completed_at":"2024-01-03T14:58:39Z"},{"name":"Run actions/checkout@v4","status":"completed","conclusion":"success","number":2,"started_at":"2024-01-03T14:58:39Z","completed_at":"2024-01-03T14:58:40Z"},{"name":"Setup Go","status":"completed","conclusion":"success","number":3,"started_at":"2024-01-03T14:58:40Z","completed_at":"2024-01-03T14:58:40Z"},{"name":"lint","status":"completed","conclusion":"failure","number":4,"started_at":"2024-01-03T14:58:40Z","completed_at":"2024-01-03T15:02:07Z"},{"name":"Run ShellCheck","status":"completed","conclusion":"skipped","number":5,"started_at":"2024-01-03T15:02:07Z","completed_at":"2024-01-03T15:02:07Z"},{"name":"Post Setup Go","status":"completed","conclusion":"skipped","number":9,"started_at":"2024-01-03T15:02:07Z","completed_at":"2024-01-03T15:02:07Z"},{"name":"Post Run actions/checkout@v4","status":"completed","conclusion":"success","number":10,"started_at":"2024-01-03T15:02:07Z","completed_at":"2024-01-03T15:02:07Z"},{"name":"Complete job","status":"completed","conclusion":"success","number":11,"started_at":"2024-01-03T15:02:07Z","completed_at":"2024-01-03T15:02:07Z"}],"check_run_url":"https://api.github.com/repos/mongodb/mongodb-atlas-kubernetes/check-runs/20128870430","labels":["ubuntu-latest"],"runner_id":6,"runner_name":"GitHub Actions 6","runner_group_id":2,"runner_group_name":"GitHub Actions","run_attempt":1,"workflow_name":"Test"},{"id":20128870607,"run_id":7398824388,"run_url":"https://api.github.com/repos/mongodb/mongodb-atlas-kubernetes/actions/runs/7398824388","node_id":"CR_kwDOEnYpJ88AAAAEr8Ywzw","head_branch":"CLOUDP-209691/oidc-auth-support","head_sha":"cf26f107757d32b3ae162bfab3f2b668d6648f5c","url":"https://api.github.com/repos/mongodb/mongodb-atlas-kubernetes/actions/jobs/20128870607","html_url":"https://github.com/mongodb/mongodb-atlas-kubernetes/actions/runs/7398824388/job/20128870607","status":"completed","conclusion":"failure","created_at":"2024-01-03T14:58:33Z","started_at":"2024-01-03T14:58:39Z","completed_at":"2024-01-03T15:01:01Z","name":"unit-tests / Unit tests","steps":[{"name":"Set up job","status":"completed","conclusion":"success","number":1,"started_at":"2024-01-03T14:58:39Z","completed_at":"2024-01-03T14:58:40Z"},{"name":"Run actions/checkout@v4","status":"completed","conclusion":"success","number":2,"started_at":"2024-01-03T14:58:40Z","completed_at":"2024-01-03T14:58:41Z"},{"name":"Cache multiple paths","status":"completed","conclusion":"success","number":3,"started_at":"2024-01-03T14:58:41Z","completed_at":"2024-01-03T14:58:44Z"},{"name":"Setup Go","status":"completed","conclusion":"success","number":4,"started_at":"2024-01-03T14:58:45Z","completed_at":"2024-01-03T14:58:45Z"},{"name":"Run go version","status":"completed","conclusion":"success","number":5,"started_at":"2024-01-03T14:58:45Z","completed_at":"2024-01-03T14:58:45Z"},{"name":"Run testing","status":"completed","conclusion":"failure","number":6,"started_at":"2024-01-03T14:58:45Z","completed_at":"2024-01-03T15:00:59Z"},{"name":"Upload coverage to Codecov","status":"completed","conclusion":"skipped","number":7,"started_at":"2024-01-03T15:00:59Z","completed_at":"2024-01-03T15:00:59Z"},{"name":"Post Setup Go","status":"completed","conclusion":"skipped","number":12,"started_at":"2024-01-03T15:00:59Z","completed_at":"2024-01-03T15:00:59Z"},{"name":"Post Cache multiple paths","status":"completed","conclusion":"skipped","number":13,"started_at":"2024-01-03T15:00:59Z","completed_at":"2024-01-03T15:00:59Z"},{"name":"Post Run actions/checkout@v4","status":"completed","conclusion":"success","number":14,"started_at":"2024-01-03T15:00:59Z","completed_at":"2024-01-03T15:00:59Z"},{"name":"Complete job","status":"completed","conclusion":"success","number":15,"started_at":"2024-01-03T15:00:59Z","completed_at":"2024-01-03T15:00:59Z"}],"check_run_url":"https://api.github.com/repos/mongodb/mongodb-atlas-kubernetes/check-runs/20128870607","labels":["ubuntu-latest"],"runner_id":8,"runner_name":"GitHub Actions 8","runner_group_id":2,"runner_group_name":"GitHub Actions","run_attempt":1,"workflow_name":"Test"},{"id":20128870828,"run_id":7398824388,"run_url":"https://api.github.com/repos/mongodb/mongodb-atlas-kubernetes/actions/runs/7398824388","node_id":"CR_kwDOEnYpJ88AAAAEr8YxrA","head_branch":"CLOUDP-209691/oidc-auth-support","head_sha":"cf26f107757d32b3ae162bfab3f2b668d6648f5c","url":"https://api.github.com/repos/mongodb/mongodb-atlas-kubernetes/actions/jobs/20128870828","html_url":"https://github.com/mongodb/mongodb-atlas-kubernetes/actions/runs/7398824388/job/20128870828","status":"completed","conclusion":"success","created_at":"2024-01-03T14:58:33Z","started_at":"2024-01-03T14:58:38Z","completed_at":"2024-01-03T14:59:59Z","name":"check-licenses / Check Licenses","steps":[{"name":"Set up job","status":"completed","conclusion":"success","number":1,"started_at":"2024-01-03T14:58:37Z","completed_at":"2024-01-03T14:58:38Z"},{"name":"Run actions/checkout@v4","status":"completed","conclusion":"success","number":2,"started_at":"2024-01-03T14:58:38Z","completed_at":"2024-01-03T14:58:39Z"},{"name":"Cache multiple paths","status":"completed","conclusion":"success","number":3,"started_at":"2024-01-03T14:58:39Z","completed_at":"2024-01-03T14:58:42Z"},{"name":"Setup Go","status":"completed","conclusion":"success","number":4,"started_at":"2024-01-03T14:58:42Z","completed_at":"2024-01-03T14:58:42Z"},{"name":"Run go version","status":"completed","conclusion":"success","number":5,"started_at":"2024-01-03T14:58:42Z","completed_at":"2024-01-03T14:58:42Z"},{"name":"Run testing","status":"completed","conclusion":"success","number":6,"started_at":"2024-01-03T14:58:42Z","completed_at":"2024-01-03T14:59:57Z"},{"name":"Post Setup Go","status":"completed","conclusion":"success","number":10,"started_at":"2024-01-03T14:59:58Z","completed_at":"2024-01-03T14:59:58Z"},{"name":"Post Cache multiple paths","status":"completed","conclusion":"success","number":11,"started_at":"2024-01-03T14:59:58Z","completed_at":"2024-01-03T14:59:58Z"},{"name":"Post Run actions/checkout@v4","status":"completed","conclusion":"success","number":12,"started_at":"2024-01-03T14:59:59Z","completed_at":"2024-01-03T14:59:59Z"},{"name":"Complete job","status":"completed","conclusion":"success","number":13,"started_at":"2024-01-03T14:59:58Z","completed_at":"2024-01-03T14:59:58Z"}],"check_run_url":"https://api.github.com/repos/mongodb/mongodb-atlas-kubernetes/check-runs/20128870828","labels":["ubuntu-latest"],"runner_id":7,"runner_name":"GitHub Actions 7","runner_group_id":2,"runner_group_name":"GitHub Actions","run_attempt":1,"workflow_name":"Test"},{"id":20128871042,"run_id":7398824388,"run_url":"https://api.github.com/repos/mongodb/mongodb-atlas-kubernetes/actions/runs/7398824388","node_id":"CR_kwDOEnYpJ88AAAAEr8Yygg","head_branch":"CLOUDP-209691/oidc-auth-support","head_sha":"cf26f107757d32b3ae162bfab3f2b668d6648f5c","url":"https://api.github.com/repos/mongodb/mongodb-atlas-kubernetes/actions/jobs/20128871042","html_url":"https://github.com/mongodb/mongodb-atlas-kubernetes/actions/runs/7398824388/job/20128871042","status":"completed","conclusion":"success","created_at":"2024-01-03T14:58:34Z","started_at":"2024-01-03T14:58:38Z","completed_at":"2024-01-03T14:58:41Z","name":"cloud-tests-filter / cloud-tests-filter","steps":[{"name":"Set up job","status":"completed","conclusion":"success","number":1,"started_at":"2024-01-03T14:58:37Z","completed_at":"2024-01-03T14:58:38Z"},{"name":"Run actions/checkout@v4","status":"completed","conclusion":"success","number":2,"started_at":"2024-01-03T14:58:38Z","completed_at":"2024-01-03T14:58:39Z"},{"name":"Run dorny/paths-filter@v2","status":"completed","conclusion":"success","number":3,"started_at":"2024-01-03T14:58:39Z","completed_at":"2024-01-03T14:58:39Z"},{"name":"Production code changed","status":"completed","conclusion":"success","number":4,"started_at":"2024-01-03T14:58:39Z","completed_at":"2024-01-03T14:58:39Z"},{"name":"Tests Filter","status":"completed","conclusion":"success","number":5,"started_at":"2024-01-03T14:58:39Z","completed_at":"2024-01-03T14:58:39Z"},{"name":"Cloud tests should run","status":"completed","conclusion":"success","number":6,"started_at":"2024-01-03T14:58:39Z","completed_at":"2024-01-03T14:58:39Z"},{"name":"Post Run actions/checkout@v4","status":"completed","conclusion":"success","number":12,"started_at":"2024-01-03T14:58:39Z","completed_at":"2024-01-03T14:58:39Z"},{"name":"Complete job","status":"completed","conclusion":"success","number":13,"started_at":"2024-01-03T14:58:39Z","completed_at":"2024-01-03T14:58:39Z"}],"check_run_url":"https://api.github.com/repos/mongodb/mongodb-atlas-kubernetes/check-runs/20128871042","labels":["ubuntu-latest"],"runner_id":9,"runner_name":"GitHub Actions 9","runner_group_id":2,"runner_group_name":"GitHub Actions","run_attempt":1,"workflow_name":"Test"},{"id":20129003009,"run_id":7398824388,"run_url":"https://api.github.com/repos/mongodb/mongodb-atlas-kubernetes/actions/runs/7398824388","node_id":"CR_kwDOEnYpJ88AAAAEr8g2AQ","head_branch":"CLOUDP-209691/oidc-auth-support","head_sha":"cf26f107757d32b3ae162bfab3f2b668d6648f5c","url":"https://api.github.com/repos/mongodb/mongodb-atlas-kubernetes/actions/jobs/20129003009","html_url":"https://github.com/mongodb/mongodb-atlas-kubernetes/actions/runs/7398824388/job/20129003009","status":"completed","conclusion":"skipped","created_at":"2024-01-03T15:02:09Z","started_at":"2024-01-03T15:02:09Z","completed_at":"2024-01-03T15:02:09Z","name":"cloud-tests","check_run_url":"https://api.github.com/repos/mongodb/mongodb-atlas-kubernetes/check-runs/20129003009","run_attempt":1,"workflow_name":"Test"}]}